Workbook
Name tgr: DCF!$C$16
Name wacc: DCF!$C$15

Sheet WACC
B1: WACC
A3: x | B3: WACC
B4: WACC = (% Equity x Cost of Equity) + (% Debt x Cost of Debt x (1 -Tax rate))
B5: Cost of Equity = Risk Free Rate + (Beta x (Expected Market Return - Risk Free Rate))
B7: Debt | D7: 32366
B8: % Debt | D8: =D7/(D7+D12) -> 0.0057059083
B9: Cost of Debt | D9: 0.024
B10: Tax Rate | D10: =DCF!K13 -> 0.17
B12: Market Cap | D12: 5640000
B13: % Equity | D13: =D12/(D12+D7) -> 0.99429409
B14: Cost of Equity | D14: =D15+(D16*D17) -> 0.144658
B15: Risk Free Rate | D15: 0.05275
B16: Beta | D16: 2.22
B17: Market Risk Premium | D17: 0.0414
B19: Debt + Equity | D19: =D7+D12 -> 5672366
A21: x | B21: WACC | D21: =(D13*D14)+(D8*(D9*(1-D10))) -> 0.14394626

Sheet DCF
B2: NVIDIA DCF
B4: Ticker | C4: NVDA | E4: Implied Share Price | F4: =O79 -> 215.30018
B5: Date | C5: =TODAY() -> 46301 | E5: Current Share Price | F5: 238.9
B6: Year end | C6: 46387 | E6: Implied Gain / (Loss) | F6: =F4/F5-1 -> -0.098785329
A8: x | B8: Assumptions
B9: Switches | F9: Conservative | J9: Street / Base | N9: Optimistic
B10: Revenue | C10: 2 | F10: Revenue '27-'28 | G10: 0.8 | N10: Revenue '27-'28 | O10: 1.2
B11: EBIT | C11: 2 | F11: Revenue 2030 | G11: 0.08 | J11: Revenue 2030 | K11: 0.15 | N11: Revenue 2030 | O11: 0.28
B12: WACC | C12: 3 | F12: EBIT '27-28 | G12: 0.9 | N12: EBIT '27-28 | O12: 1.05
B13: TGR | C13: 2 | J13: Taxes | K13: 0.17
F14: WACC | G14: =K14+0.5% -> 0.14894626 | J14: WACC | K14: =WACC!D21 -> 0.14394626 | N14: WACC | O14: 0.125
B15: WACC | C15: =CHOOSE($C$12,G14,K14,O14) -> 0.125 | F15: TGR | G15: 0.02 | J15: TGR | K15: 0.025 | N15: TGR | O15: 0.03
B16: TGR | C16: =CHOOSE($C$13,G15,K15,O15) -> 0.025
K17: 1 | L17: =K17+1 -> 2 | M17: =L17+1 -> 3 | N17: =M17+1 -> 4 | O17: =N17+1 -> 5
A18: x | B18: Income Statement (12/31 CYE) | C18: 2018 | D18: 2019 | E18: 2020 | F18: 2021 | G18: 2022 | H18: 2023 | I18: 2024 | J18: 2025 | K18: 2026 | L18: 2027 | M18: 2028 | N18: 2029 | O18: 2030
B19: Revenue | C19: =(11/12)*IS!C8+(1/12)*IS!B8 -> 11549.167 | D19: =(11/12)*IS!D8+(1/12)*IS!C8 -> 10984.5 | E19: =(11/12)*IS!E8+(1/12)*IS!D8 -> 16195.25 | F19: =(11/12)*IS!F8+(1/12)*IS!E8 -> 26060.75 | G19: =(11/12)*IS!G8+(1/12)*IS!F8 -> 26969 | H19: =(11/12)*IS!H8+(1/12)*IS!G8 -> 58093 | I19: =(11/12)*IS!I8+(1/12)*IS!H8 -> 124699.08 | J19: =(11/12)*IS!J8+(1/12)*IS!I8 -> 208817.92 | K19: 395011 | L19: 657635 | M19: 874107 | N19: 822323 | O19: 918183
B20: % growth | C20: - | D20: =D19/C19-1 -> -0.048892416 | E20: =E19/D19-1 -> 0.47437298 | F20: =F19/E19-1 -> 0.60916009 | G20: =G19/F19-1 -> 0.034851261 | H20: =H19/G19-1 -> 1.1540658 | I20: =I19/H19-1 -> 1.1465423 | J20: =J19/I19-1 -> 0.67457459 | K20: =K19/J19-1 -> 0.89165282 | ... O20: =O19/N19-1 -> 0.1165722
B22: EBIT | C22: =(11/12)*IS!C17+(1/12)*IS!B17 -> 3754.5 | D22: =(11/12)*IS!D17+(1/12)*IS!C17 -> 2925.8333 | E22: =(11/12)*IS!E17+(1/12)*IS!D17 -> 4391.5 | F22: =(11/12)*IS!F17+(1/12)*IS!E17 -> 9581.9167 | G22: =(11/12)*IS!G17+(1/12)*IS!F17 -> 4708.75 | H22: =(11/12)*IS!H17+(1/12)*IS!G17 -> 30576.333 | I22: =(11/12)*IS!I17+(1/12)*IS!H17 -> 77412.917 | J22: =(11/12)*IS!J17+(1/12)*IS!I17 -> 126309.17 | K22: 257264 | L22: 426153 | M22: 580666 | N22: 565959 | O22: 605277
B23: % of sales | C23: =C22/C19 -> 0.32508839 | D23: =D22/D19 -> 0.26636017 | E23: =E22/E19 -> 0.27115975 | F23: =F22/F19 -> 0.36767617 | G23: =G22/G19 -> 0.17459861 | H23: =H22/H19 -> 0.52633421 | I23: =I22/I19 -> 0.6207978 | J23: =J22/J19 -> 0.60487706 | ... O23: =O22/O19 -> 0.65921173
A25: x | B25: Cash Flow Items | C25: =C18 -> 2018 | D25: =D18 -> 2019 | E25: =E18 -> 2020 | F25: =F18 -> 2021 | G25: =G18 -> 2022 | H25: =H18 -> 2023 | I25: =I18 -> 2024 | J25: =J18 -> 2025 | ... Q25: =Q18 -> 0
B26: D&A | C26: =(11/12)*CFS!C9+(1/12)*CFS!B9 -> 256.75 | D26: =(11/12)*CFS!D9+(1/12)*CFS!C9 -> 371.08333 | E26: =(11/12)*CFS!E9+(1/12)*CFS!D9 -> 1038.25 | F26: =(11/12)*CFS!F9+(1/12)*CFS!E9 -> 1167.6667 | G26: =(11/12)*CFS!G9+(1/12)*CFS!F9 -> 1513.1667 | H26: =(11/12)*CFS!H9+(1/12)*CFS!G9 -> 1511 | I26: =(11/12)*CFS!I9+(1/12)*CFS!H9 -> 1834.3333 | J26: =(11/12)*CFS!J9+(1/12)*CFS!I9 -> 2761.4167
B27: % of sales | C27: =C26/C19 -> 0.022231041 | D27: =D26/D19 -> 0.033782451 | E27: =E26/E19 -> 0.064108303 | F27: =F26/F19 -> 0.044805566 | G27: =G26/G19 -> 0.05610763 | H27: =H26/H19 -> 0.026010018 | I27: =I26/I19 -> 0.014710079 | J27: =J26/J19 -> 0.013224041
B29: CapEx | C29: =-((11/12)*CFS!C31+(1/12)*CFS!B31) -> 599.41667 | D29: =-((11/12)*CFS!D31+(1/12)*CFS!C31) -> 498.25 | E29: =-((11/12)*CFS!E31+(1/12)*CFS!D31) -> 1074.75 | F29: =-((11/12)*CFS!F31+(1/12)*CFS!E31) -> 988.66667 | G29: =-((11/12)*CFS!G31+(1/12)*CFS!F31) -> 1761.5833 | H29: =-((11/12)*CFS!H31+(1/12)*CFS!G31) -> 1132.6667 | I29: =-((11/12)*CFS!I31+(1/12)*CFS!H31) -> 3055.4167 | J29: =-((11/12)*CFS!J31+(1/12)*CFS!I31) -> 5808.1667
B30: % of sales | C30: =C29/C19 -> 0.051901292 | D30: =D29/D19 -> 0.04535937 | E30: =E29/E19 -> 0.066362051 | F30: =F29/F19 -> 0.037937 | G30: =G29/G19 -> 0.065318823 | H30: =H29/H19 -> 0.019497472 | I30: =I29/I19 -> 0.024502319 | J30: =J29/J19 -> 0.027814503
B32: Change in NWC raw | C32: =SUM(CFS!B17:B21) -> -296 | D32: =SUM(CFS!C17:C21) -> -859 | E32: =SUM(CFS!D17:D21) -> 689 | F32: =SUM(CFS!E17:E21) -> -866 | G32: =SUM(CFS!F17:F21) -> -3555 | H32: =SUM(CFS!G17:G21) -> -2459 | I32: =SUM(CFS!H17:H21) -> -4236 | J32: =SUM(CFS!I17:I21) -> -10604 | K32: =SUM(CFS!J17:J21) -> -17793
B33: Change in NWC | C33: =-((11/12*D32)+(1/12*C32)) -> 812.08333 | D33: =-((11/12*E32)+(1/12*D32)) -> -560 | E33: =-((11/12*F32)+(1/12*E32)) -> 736.41667 | F33: =-((11/12*G32)+(1/12*F32)) -> 3330.9167 | G33: =-((11/12*H32)+(1/12*G32)) -> 2550.3333 | H33: =-((11/12*I32)+(1/12*H32)) -> 4087.9167 | I33: =-((11/12*J32)+(1/12*I32)) -> 10073.333
B34: % of sales | C34: =C33/C19 -> 0.070315319 | D34: =D33/D19 -> -0.050980928 | E34: =E33/E19 -> 0.045471152 | F34: =F33/F19 -> 0.12781354 | G34: =G33/G19 -> 0.094565365 | H34: =H33/H19 -> 0.07036849 | I34: =I33/I19 -> 0.080781134
B35: % of change in sales | D35: =D33/(D19-C19) -> 0.99173554 | E35: =E33/(E19-D19) -> 0.14132642 | F35: =F33/(F19-E19) -> 0.33763283 | G35: =G33/(G19-F19) -> 2.807964 | H35: =H33/(H19-G19) -> 0.13134291 | I35: =I33/(I19-H19) -> 0.15123744
A38: x | B38: DCF | C38: =C18 -> 2018 | D38: =D18 -> 2019 | E38: =E18 -> 2020 | F38: =F18 -> 2021 | G38: =G18 -> 2022 | H38: =H18 -> 2023 | I38: =I18 -> 2024 | J38: =J18 -> 2025 | ... T38: =T18 -> 0 | U38: 2031 | V38: 2032
B39: Revenue | C39: =C19 -> 11549.167 | D39: =D19 -> 10984.5 | E39: =E19 -> 16195.25 | F39: =F19 -> 26060.75 | G39: =G19 -> 26969 | H39: =H19 -> 58093 | I39: =I19 -> 124699.08 | J39: =J19 -> 208817.92 | K39: =J39*(1+K40) -> 395011 | L39: =K39*(1+L40) -> 657635 | M39: =L39*(1+M40) -> 874107 | N39: =M39*(1+N40) -> 1083528.8 | O39: =N39*(1+O40) -> 1246058.1
B40: % growth | C40: =C20 -> - | D40: =D20 -> -0.048892416 | E40: =E20 -> 0.47437298 | F40: =F20 -> 0.60916009 | G40: =G20 -> 0.034851261 | H40: =H20 -> 1.1540658 | I40: =I20 -> 1.1465423 | J40: =J20 -> 0.67457459 | K40: =OFFSET(K40,$C$10,0) -> 0.89165282 | L40: =OFFSET(L40,$C$10,0) -> 0.66485237 | M40: =OFFSET(M40,$C$10,0) -> 0.3291674 | N40: =OFFSET(N40,$C$10,0) -> 0.2395837 | O40: =OFFSET(O40,$C$10,0) -> 0.15
B41: Conservative Case | K41: =K42 -> 0.89165282 | L41: =L42*$G$10 -> 0.5318819 | M41: =M42*$G$10 -> 0.26333392 | N41: =N42*$G$10 -> 0.19166696 | O41: =G11 -> 0.08
B42: Street Case | K42: =K20 -> 0.89165282 | L42: =L20 -> 0.66485237 | M42: =M20 -> 0.3291674 | N42: =M42-($M$42-$O$42)/($O$38-$M$38) -> 0.2395837 | O42: =K11 -> 0.15
B43: Optimistic Case | K43: =K42 -> 0.89165282 | L43: =L42*$O$10 -> 0.79782285 | M43: =M42*$O$10 -> 0.39500087 | N43: =N42*$O$10 -> 0.28750044 | O43: =O11 -> 0.28
B45: EBIT | C45: =C22 -> 3754.5 | D45: =D22 -> 2925.8333 | E45: =E22 -> 4391.5 | F45: =F22 -> 9581.9167 | G45: =G22 -> 4708.75 | H45: =H22 -> 30576.333 | I45: =I22 -> 77412.917 | J45: =J22 -> 126309.17 | K45: =K46*K39 -> 257264 | L45: =L46*L39 -> 426153 | M45: =M46*M39 -> 566428.67 | N45: =N46*N39 -> 702135.75 | O45: =O46*O39 -> 807456.11
B46: % of sales | C46: =C45/C19 -> 0.32508839 | D46: =D45/D19 -> 0.26636017 | E46: =E45/E19 -> 0.27115975 | F46: =F45/F19 -> 0.36767617 | G46: =G45/G19 -> 0.17459861 | H46: =H45/H19 -> 0.52633421 | I46: =I45/I19 -> 0.6207978 | J46: =J45/J19 -> 0.60487706 | K46: =OFFSET(K46,$C$11,0) -> 0.65128313 | L46: =OFFSET(L46,$C$11,0) -> 0.64800839 | M46: =OFFSET(M46,$C$11,0) -> 0.64800839 | N46: =OFFSET(N46,$C$11,0) -> 0.64800839 | O46: =OFFSET(O46,$C$11,0) -> 0.64800839
B47: Conservative Case | K47: =K48 -> 0.65128313 | L47: =L48*$G$12 -> 0.58320755 | M47: =L47 -> 0.58320755 | N47: =M47 -> 0.58320755 | O47: =N47 -> 0.58320755
B48: Street Case | K48: =K23 -> 0.65128313 | L48: =L23 -> 0.64800839 | M48: =L48 -> 0.64800839 | N48: =M48 -> 0.64800839 | O48: =N48 -> 0.64800839
B49: Optimistic Case | K49: =K48 -> 0.65128313 | L49: =L48*$O$12 -> 0.68040881 | M49: =L49 -> 0.68040881 | N49: =M49 -> 0.68040881 | O49: =N49 -> 0.68040881
B51: Taxes | K51: =K52*K45 -> 39618.656 | L51: =L52*L45 -> 67332.174 | M51: =M52*M45 -> 91761.445 | N51: =N52*N45 -> 116554.53 | O51: =O52*O45 -> 137267.54
B52: % of EBIT | K52: 0.154 | L52: =K52+($O$52-$K$52)/($O$38-$K$38) -> 0.158 | M52: =L52+($O$52-$K$52)/($O$38-$K$38) -> 0.162 | N52: =M52+($O$52-$K$52)/($O$38-$K$38) -> 0.166 | O52: 0.17
B54: EBIAT | K54: =K45-K51 -> 217645.34 | L54: =L45-L51 -> 358820.83 | M54: =M45-M51 -> 474667.23 | N54: =N45-N51 -> 585581.21 | O54: =O45-O51 -> 670188.57
B56: D&A | C56: =C26 -> 256.75 | D56: =D26 -> 371.08333 | E56: =E26 -> 1038.25 | F56: =F26 -> 1167.6667 | G56: =G26 -> 1513.1667 | H56: =H26 -> 1511 | I56: =I26 -> 1834.3333 | J56: =J26 -> 2761.4167 | K56: =K57*K$39 -> 7102.8426 | L56: =L57*L$39 -> 11825.184 | M56: =M57*M$39 -> 15717.65 | N56: =N57*N$39 -> 19483.342 | O56: =O57*O$39 -> 22405.843
B57: % of sales | C57: =C56/C39 -> 0.022231041 | D57: =D56/D39 -> 0.033782451 | E57: =E56/E39 -> 0.064108303 | F57: =F56/F39 -> 0.044805566 | G57: =G56/G39 -> 0.05610763 | H57: =H56/H39 -> 0.026010018 | I57: =I56/I39 -> 0.014710079 | J57: =J56/J39 -> 0.013224041 | K57: =AVERAGE(H57:J57) -> 0.017981379 | L57: =K57 -> 0.017981379 | M57: =L57 -> 0.017981379 | N57: =M57 -> 0.017981379 | O57: =N57 -> 0.017981379
B59: CapEx | C59: =C29 -> 599.41667 | D59: =D29 -> 498.25 | E59: =E29 -> 1074.75 | F59: =F29 -> 988.66667 | G59: =G29 -> 1761.5833 | H59: =H29 -> 1132.6667 | I59: =I29 -> 3055.4167 | J59: =J29 -> 5808.1667 | K59: =K60*K$39 -> 9455.8121 | L59: =L60*L$39 -> 15742.531 | M59: =M60*M$39 -> 20924.459 | N59: =N60*N$39 -> 25937.618 | O59: =O60*O$39 -> 29828.261
B60: % of sales | C60: =C59/C39 -> 0.051901292 | D60: =D59/D39 -> 0.04535937 | E60: =E59/E39 -> 0.066362051 | F60: =F59/F39 -> 0.037937 | G60: =G59/G39 -> 0.065318823 | H60: =H59/H39 -> 0.019497472 | I60: =I59/I39 -> 0.024502319 | J60: =J59/J39 -> 0.027814503 | K60: =AVERAGE(H60:J60) -> 0.023938098 | L60: =K60 -> 0.023938098 | M60: =L60 -> 0.023938098 | N60: =M60 -> 0.023938098 | O60: =N60 -> 0.023938098
B62: Change in NWC | C62: =C33 -> 812.08333 | D62: =D33 -> -560 | E62: =E33 -> 736.41667 | F62: =F33 -> 3330.9167 | G62: =G33 -> 2550.3333 | H62: =H33 -> 4087.9167 | I62: =I33 -> 10073.333 | J62: - | K62: =K63*K$39 -> 32353.374 | L62: =L63*L$39 -> 53863.592 | M62: =M63*M$39 -> 71593.731 | N62: =N63*N$39 -> 88746.421 | O62: =O63*O$39 -> 102058.38
B63: % of sales | C63: =C62/C39 -> 0.070315319 | D63: =D62/D39 -> -0.050980928 | E63: =E62/E39 -> 0.045471152 | F63: =F62/F39 -> 0.12781354 | G63: =G62/G39 -> 0.094565365 | H63: =H62/H39 -> 0.07036849 | I63: =I62/I39 -> 0.080781134 | J63: - | K63: =AVERAGE(G63:I63) -> 0.081904996 | L63: =K63 -> 0.081904996 | M63: =L63 -> 0.081904996 | N63: =M63 -> 0.081904996 | O63: =N63 -> 0.081904996
B65: Unlevered FCF | K65: =K54+K56-K59-K62 -> 182939 | L65: =L54+L56-L59-L62 -> 301039.89 | M65: =M54+M56-M59-M62 -> 397866.69 | N65: =N54+N56-N59-N62 -> 490380.52 | O65: =O54+O56-O59-O62 -> 560707.77
B66: Present Value of FCF | K66: =K65/(1+wacc)^K69 -> 180412.85 | L66: =L65/(1+wacc)^L69 -> 276038.78 | M66: =M65/(1+wacc)^M69 -> 324288.18 | N66: =N65/(1+wacc)^N69 -> 355282.83 | O66: =O65/(1+wacc)^O69 -> 361097.99
B68: Period | K68: =YEARFRAC(C5,C6) -> 0.23611111 | L68: =K68+1 -> 1.2361111 | M68: =L68+1 -> 2.2361111 | N68: =M68+1 -> 3.2361111 | O68: =N68+1 -> 4.2361111
B69: Discount Period | K69: =K68/2 -> 0.11805556 | L69: =K68+0.5 -> 0.73611111 | M69: =L69+1 -> 1.7361111 | N69: =M69+1 -> 2.7361111 | O69: =N69+1 -> 3.7361111
B71: Terminal Value | O71: =(O65*(1+tgr))/(wacc-tgr) -> 5747254.6
B72: Present Value of terminal value | O72: =O71/(1+wacc)^O69 -> 3701254.4
B73: Enterprise Value | O73: =SUM(K66:O66)+O72 -> 5198375
B74: (+) Cash | O74: 62556
B75: (-) Debt | O75: =WACC!D7 -> 32366
B76: Equity Value | O76: =O73+O74-O75 -> 5228565
B78: Diluted Shares | O78: 24285
B79: Implied Stock Price | O79: =O76/O78 -> 215.30018

Sheet IS
A1: NVIDIA Corp
B4: =11/12 -> 0.91666667 | C4: =1/12 -> 0.083333333
A5: Consolidated Statements of Income - USD ($)
A6: shares in Millions, $ in Millions | B6: Jan. 28, 2018 | C6: Jan. 27, 2019 | D6: Jan. 26, 2020 | E6: Jan. 31, 2021 | F6: Jan. 30, 2022 | G6: Jan. 29, 2023 | H6: Jan. 28, 2024 | I6: Jan. 26, 2025 | J6: Jan. 25, 2026
A7: Income Statement [Abstract]
A8: Revenue | B8: 9714 | C8: 11716 | D8: 10918 | E8: 16675 | F8: 26914 | G8: 26974 | H8: 60922 | I8: 130497 | J8: 215938
A9: Cost of revenue | B9: 3892 | C9: 4545 | D9: 4150 | E9: 6279 | F9: 9439 | G9: 11618 | H9: 16621 | I9: 32639 | J9: 62475
A10: Gross profit | B10: 5822 | C10: 7171 | D10: 6768 | E10: 10396 | F10: 17475 | G10: 15356 | H10: 44301 | I10: 97858 | J10: 153463
A11: Operating expenses
A12: Research and development | B12: 1797 | C12: 2376 | D12: 2829 | E12: 3924 | F12: 5268 | G12: 7339 | H12: 8675 | I12: 12914 | J12: 18497
A13: Sales, general and administrative | B13: 815 | C13: 991 | D13: 1093 | E13: 1940 | F13: 2166 | G13: 2440 | H13: 2654 | I13: 3491 | J13: 4579
A14: Acquisition termination cost | E14: 0 | F14: 0 | G14: 1353
A15: Restructuring and other charges
A16: Total operating expenses | B16: 2612 | C16: 3367 | D16: 3922 | E16: 5864 | F16: 7434 | G16: 11132 | H16: 11329 | I16: 16405 | J16: 23076
A17: Operating income | B17: 3210 | C17: 3804 | D17: 2846 | E17: 4532 | F17: 10041 | G17: 4224 | H17: 32972 | I17: 81453 | J17: 130387
A18: Interest income | B18: 69 | C18: 136 | D18: 178 | E18: 57 | F18: 29 | G18: 267 | H18: 866 | I18: 1786 | J18: 2300
A19: Interest expense | B19: -61 | C19: -58 | D19: -52 | E19: -184 | F19: -236 | G19: -262 | H19: -257 | I19: -247 | J19: -259
A20: Other income, net | B20: -22 | C20: 14 | D20: -2 | E20: 4 | F20: 107 | G20: -48 | H20: 237 | I20: 1034 | J20: 9022
A21: Total other income, net | B21: -14 | C21: 92 | D21: 124 | E21: -123 | F21: -100 | G21: -43 | H21: 846 | I21: 2573 | J21: 11063
A22: Income before income tax | B22: 3196 | C22: 3896 | D22: 2970 | E22: 4409 | F22: 9941 | G22: 4181 | H22: 33818 | I22: 84026 | J22: 141450
A23: Income tax expense | B23: 149 | C23: -245 | D23: 174 | E23: 77 | F23: 189 | G23: -187 | H23: 4058 | I23: 11146 | J23: 21383
A24: Net income | B24: 3047 | C24: 4141 | D24: 2796 | E24: 4332 | F24: 9752 | G24: 4368 | H24: 29760 | I24: 72880 | J24: 120067
A25: Net income per share:
A26: Basic (in USD per share) | B26: 5.09 | C26: 6.81 | D26: 4.59 | E26: 1.76 | F26: 3.91 | G26: 1.76 | H26: 1.21 | I26: 2.97 | J26: 4.93
A27: Diluted (in USD per share) | B27: 4.82 | C27: 6.63 | D27: 4.52 | E27: 1.73 | F27: 3.85 | G27: 1.74 | H27: 1.19 | I27: 2.94 | J27: 4.9
A28: Weighted average shares used in per share computation:
A29: Basic (in shares) | B29: 599 | C29: 608 | D29: 609 | E29: 2467 | F29: 2496 | G29: 2487 | H29: 24690 | I29: 24555 | J29: 24359
A30: Diluted (in shares) | B30: 632 | C30: 625 | D30: 618 | E30: 2510 | F30: 2535 | G30: 2507 | H30: 24940 | I30: 24804 | J30: 24514
A34: \

Sheet CFS
A1: Nvidia Corp
A3: Consolidated Statements of Cash Flows - USD ($) | J3: 12 Months Ended
A4: $ in Millions | B4: Jan. 28, 2018 | C4: Jan. 27, 2019 | D4: Jan. 26, 2020 | E4: Jan. 31, 2021 | F4: Jan. 30, 2022 | G4: Jan. 29, 2023 | H4: Jan. 28, 2024 | I4: Jan. 26, 2025 | J4: Jan. 25, 2026
A5: Cash flows from operating activities:
A6: Net income | B6: 3047 | C6: 4141 | D6: 2796 | E6: 4332 | F6: 9752 | G6: 4368 | H6: 29760 | I6: 72880 | J6: 120067
A7: Adjustments to reconcile net income to net cash provided by operating activities:
A8: Stock-based compensation expense | B8: 391 | C8: 557 | D8: 844 | E8: 1397 | F8: 2004 | G8: 2709 | H8: 3549 | I8: 4737 | J8: 6386
A9: Depreciation and amortization | B9: 199 | C9: 262 | D9: 381 | E9: 1098 | F9: 1174 | G9: 1544 | H9: 1508 | I9: 1864 | J9: 2843
A10: Gains on non-marketable equity securities and publicly-held equity securities, net | H10: -238 | I10: -1030 | J10: -8918
A11: Acquisition termination cost | E11: 0 | F11: 0 | G11: 1353
A12: Losses (gains) on investments in non-affiliates, net | E12: 0 | F12: -100 | G12: 45
A13: Loss on early debt conversions | B13: 19 | C13: 0 | D13: 0
A14: Deferred income taxes | B14: -359 | C14: -315 | D14: 18 | E14: -282 | F14: -406 | G14: -2164 | H14: -2489 | I14: -4477 | J14: -1424
A15: Other | B15: 20 | C15: -45 | D15: 5 | E15: -20 | F15: 47 | G15: -7 | H15: -278 | I15: -502 | J15: -287
A16: Changes in operating assets and liabilities, net of acquisitions:
A17: Accounts receivable | B17: -440 | C17: -149 | D17: -233 | E17: -550 | F17: -2215 | G17: 822 | H17: -6172 | I17: -13063 | J17: -15399
A18: Inventories | B18: 0 | C18: -776 | D18: 597 | E18: -524 | F18: -774 | G18: -2554 | H18: -98 | I18: -4781 | J18: -11324
A19: Prepaid expenses and other assets | B19: 21 | C19: -55 | D19: 77 | E19: -394 | F19: -1715 | G19: -1517 | H19: -1522 | I19: -395 | J19: 577
A20: Accounts payable | B20: 90 | C20: -135 | D20: 194 | E20: 312 | F20: 568 | G20: -551 | H20: 1531 | I20: 3357 | J20: 3096
A21: Accrued and other current liabilities | B21: 33 | C21: 256 | D21: 54 | E21: 290 | F21: 581 | G21: 1341 | H21: 2025 | I21: 4278 | J21: 5257
A22: Other long-term liabilities | B22: 481 | C22: 2 | D22: 28 | E22: 163 | F22: 192 | G22: 252 | H22: 514 | I22: 1221 | J22: 1844
A23: Net cash provided by operating activities | B23: 3502 | C23: 3743 | D23: 4761 | E23: 5822 | F23: 9108 | G23: 5641 | H23: 28090 | I23: 64089 | J23: 102718
A24: Cash flows from investing activities:
A25: Proceeds from sales of marketable securities | B25: 863 | C25: 428 | D25: 3365 | E25: 527 | F25: 1023 | G25: 1806 | H25: 50 | I25: 495 | J25: 15157
A26: Proceeds from maturities of marketable securities | B26: 1078 | C26: 7232 | D26: 4744 | E26: 8792 | F26: 15197 | G26: 19425 | H26: 9732 | I26: 11195 | J26: 11226
A27: Proceeds from sales of non-marketable equity securities | H27: 1 | I27: 171 | J27: 84
A28: Purchases of marketable securities | B28: -36 | C28: -11148 | D28: -1461 | E28: -19308 | F28: -24787 | G28: -11897 | H28: -18211 | I28: -26575 | J28: -40616
A29: Purchases of non-marketable equity securities | H29: -862 | I29: -1486 | J29: -17502
A30: Groq, Inc. | H30: 0 | I30: 0 | J30: -13000
A31: Purchases related to property and equipment and intangible assets | B31: -593 | C31: -600 | D31: -489 | E31: -1128 | F31: -976 | G31: -1833 | H31: -1069 | I31: -3236 | J31: -6042
A32: Investments and other, net | B32: -36 | C32: -9 | D32: -14 | E32: -34 | F32: -24 | G32: -77
A33: Acquisitions, net of cash acquired | E33: -8524 | F33: -263 | G33: -49 | H33: -83 | I33: -1007 | J33: -1535
A34: Proceeds from sale of long-lived assets and investments | B34: 2 | C34: 0 | D34: 0
A35: Other | H35: -124 | I35: 22 | J35: 0
A36: Net cash used in investing activities | B36: 1278 | C36: -4097 | D36: 6145 | E36: -19675 | F36: -9830 | G36: 7375 | H36: -10566 | I36: -20421 | J36: -52228
A37: Cash flows from financing activities:
A38: Proceeds related to employee stock plans | E38: 194 | F38: 281 | G38: 355 | H38: 403 | I38: 490 | J38: 644
A39: Payments related to repurchases of common stock | B39: -909 | C39: -1579 | D39: 0 | E39: 0 | F39: 0 | G39: -10039 | H39: -9533 | I39: -33706 | J39: -40086
A40: Payments related to employee stock plan taxes | B40: 139 | C40: 137 | D40: 149 | H40: -2783 | I40: -6930 | J40: -7948
A41: Payments related to tax on restricted stock units | B41: -612 | C41: -1032 | D41: -551 | E41: -942 | F41: -1904 | G41: -1475
A42: Repayment of Convertible Notes | B42: -812 | C42: -16 | D42: 0
A43: Dividends paid | B43: -341 | C43: -371 | D43: -390 | E43: -395 | F43: -399 | G43: -398 | H43: -395 | I43: -834 | J43: -974
A44: Principal payments on property and equipment and intangible assets | E44: -17 | F44: -83 | G44: -58 | H44: -74 | I44: -129 | J44: -101
A45: Repayment of debt | E45: 0 | F45: -1000 | G45: 0 | H45: -1250 | I45: -1250 | J45: 0
A46: Issuance of debt, net of issuance costs | E46: 4968 | F46: 4977 | G46: 0
A47: Other | B47: -9 | C47: -5 | D47: 0 | E47: -4 | F47: -7 | G47: -2 | H47: -1 | I47: 0 | J47: -9
A48: Net cash used in financing activities | B48: -2544 | C48: -2866 | D48: -792 | E48: 3804 | F48: 1865 | G48: -11617 | H48: -13633 | I48: -42359 | J48: -48474
A49: Change in cash and cash equivalents | B49: 2236 | C49: -3220 | D49: 10114 | E49: -10049 | F49: 1143 | G49: 1399 | H49: 3891 | I49: 1309 | J49: 2016
A50: Cash and cash equivalents at beginning of period | B50: 1766 | C50: 4002 | D50: 782 | E50: 10896 | F50: 847 | G50: 1990 | H50: 3389 | I50: 7280 | J50: 8589
A51: Cash and cash equivalents at end of period | B51: 4002 | C51: 782 | D51: 10896 | E51: 847 | F51: 1990 | G51: 3389 | H51: 7280 | I51: 8589 | J51: 10605
A52: Supplemental disclosures of cash flow information:
A53: Cash paid for income taxes, net | B53: 22 | C53: 61 | D53: 176 | E53: 249 | F53: 396 | G53: 1404 | H53: 6549 | I53: 15118 | J53: 20288
B54: 55 | C54: 55 | D54: 54 | E54: 138 | F54: 246 | G54: 254
B56: 36 | C56: 76 | D56: 212
